flamapy/commands/__init__.py
flamapy/interfaces/python/__init__.py
flamapy/interfaces/python/flamapy_feature_model.py
flamapy-2.0.1.dist-info/METADATA
flamapy-2.0.1.dist-info/WHEEL
flamapy-2.0.1.dist-info/entry_points.txt
flamapy-2.0.1.dist-info/top_level.txt
flamapy-2.0.1.dist-info/RECORD
