Metadata-Version: 2.1
Name: flamapy
Version: 2.0.1
Summary: Flamapy feature model is a distribution of the flama framework containing all plugins required to analyze feature models. It also offers a richier API and a complete command line interface and documentation.
Home-page: https://github.com/flamapy/flamapy-feature-model
Author: Flamapy
Author-email: flamapy@us.es
License: UNKNOWN
Platform: UNKNOWN
Classifier: Programming Language :: Python :: 3
Classifier: License :: OSI Approved :: GNU General Public License v3 or later (GPLv3+)
Classifier: Operating System :: OS Independent
Requires-Python: >=3.9
Provides-Extra: dev
